ledger_rest_api_dev-0.1.10.dist-info/DESCRIPTION.rst
ledger_rest_api_dev-0.1.10.dist-info/METADATA
ledger_rest_api_dev-0.1.10.dist-info/RECORD
ledger_rest_api_dev-0.1.10.dist-info/WHEEL
ledger_rest_api_dev-0.1.10.dist-info/metadata.json
ledger_rest_api_dev-0.1.10.dist-info/top_level.txt
sovrin_client_rest/__init__.py
sovrin_client_rest/__metadata__.py
sovrin_client_rest/api.py
sovrin_client_rest/client_storage.py
sovrin_client_rest/config_example.py
sovrin_client_rest/example.py
sovrin_client_rest/exceptions.py
sovrin_client_rest/persistent_client.py
sovrin_client_rest/requirements.txt
sovrin_client_rest/rest_server.py
sovrin_client_rest/sovrin_client_rest_config.py
sovrin_client_rest/start_pool.py
sovrin_client_rest/util.py
sovrin_client_rest/wallet_operation_builder.py
sovrin_client_rest/test/__init__.py
sovrin_client_rest/test/conftest.py
sovrin_client_rest/test/constants.py
sovrin_client_rest/test/helper.py
sovrin_client_rest/test/test_identity.py
