Metadata-Version: 2.0
Name: ledger-rest-api-dev
Version: 0.1.10
Summary: REST wrapper for Sovrin client
Home-page: https://github.com/evernym/sovrin-client-rest
Author: Evernym, Inc.
Author-email: dev@evernym.us
License: Apache 2.0
Keywords: Sovrin Client REST
Platform: UNKNOWN
Requires-Dist: aiohttp
Requires-Dist: requests
Requires-Dist: psutil
Requires-Dist: indy-node (==1.0.28)
